VideoAutoencoder/Model.py
VideoAutoencoder/__init__.py
VideoAutoencoder/Utils/__init__.py
VideoAutoencoder/Utils/safe.py
videoautoencoder-0.3.0.dist-info/METADATA
videoautoencoder-0.3.0.dist-info/WHEEL
videoautoencoder-0.3.0.dist-info/licenses/LICENSE
videoautoencoder-0.3.0.dist-info/RECORD
